beylerXomg/__init__.py
beylerXomg/matematik/AsalMi.py
beylerXomg/matematik/Fibonacci.py
beylerXomg/matematik/Permutasyon.py
beylerXomg/matematik/Pi.py
beylerXomg/matematik/__init__.py
beylerXomg/oynat/__init__.py
beylerXomg/oynat/KendinOynat/__init__.py
beylerXomg/oynat/KendinOynat/cal.py
beylerXomg/oynat/kategori/__init__.py
beylerXomg/oynat/kategori/hayvanlar/BozKurt_1.wav
beylerXomg/oynat/kategori/hayvanlar/__init__.py
beylerXomg/oynat/kategori/hayvanlar/arılar_1.wav
beylerXomg/oynat/kategori/hayvanlar/at_1.wav
beylerXomg/oynat/kategori/hayvanlar/fil_1.wav
beylerXomg/oynat/kategori/hayvanlar/fil_2.wav
beylerXomg/oynat/kategori/hayvanlar/kaplan_1.wav
beylerXomg/oynat/kategori/hayvanlar/kaplan_2.wav
beylerXomg/oynat/kategori/hayvanlar/kartal_1.wav
beylerXomg/oynat/kategori/hayvanlar/kedi_1.wav
beylerXomg/oynat/kategori/hayvanlar/kedi_2.wav
beylerXomg/oynat/kategori/hayvanlar/kuzu_1.wav
beylerXomg/oynat/kategori/hayvanlar/köpek_1.wav
beylerXomg/oynat/kategori/hayvanlar/köpek_2.wav
beylerXomg/oynat/kategori/hayvanlar/köpek_3.wav
beylerXomg/oynat/kategori/hayvanlar/orangutan_1.wav
beylerXomg/oynat/kategori/hayvanlar/sesler.py
beylerXomg/oynat/kategori/hayvanlar/ördek_1.wav
beylerXomg/oynat/kategori/milyoner/__init__.py
beylerXomg/oynat/kategori/milyoner/dogru_1.wav
beylerXomg/oynat/kategori/milyoner/dogru_2.wav
beylerXomg/oynat/kategori/milyoner/dogru_3.wav
beylerXomg/oynat/kategori/milyoner/dogru_4.wav
beylerXomg/oynat/kategori/milyoner/dogru_5.wav
beylerXomg/oynat/kategori/milyoner/dogru_6.wav
beylerXomg/oynat/kategori/milyoner/sesler.py
beylerXomg/oynat/kategori/milyoner/tıklama_1.wav
beylerXomg/oynat/kategori/milyoner/tıklama_2.wav
beylerXomg/oynat/kategori/milyoner/tıklama_3.wav
beylerXomg/oynat/kategori/milyoner/tıklama_4.wav
beylerXomg/oynat/kategori/milyoner/yanlıs_1.wav
beylerXomg/oynat/kategori/milyoner/yanlıs_2.wav
beylerXomg/oynat/kategori/omgOzel/__init__.py
beylerXomg/oynat/kategori/omgOzel/omg-duz.wav
beylerXomg/oynat/kategori/omgOzel/omg-yankılı.wav
beylerxomg-1.1.0.dist-info/licenses/LICENSE
beylerxomg-1.1.0.dist-info/METADATA
beylerxomg-1.1.0.dist-info/WHEEL
beylerxomg-1.1.0.dist-info/top_level.txt
beylerxomg-1.1.0.dist-info/RECORD
